{
    "PipelineName": "DualBokehJpegSnapshot",
    "NodesList": {
      "Node": [
        {
            "NodeName": "com.xiaomi.plugin.capbokeh",
            "NodeInstance": "CapbokehInstance0",
            "InputFormat": "YUV420_NV12",
            "OutputFormat": "YUV420_NV12",
            "NodeProperty":[
            {
                "NodePropertyName":"NodeMask",
                "NodePropertyValue":4
            }
            ]
        },
        {
            "NodeName": "com.xiaomi.plugin.offlinepostproc",
            "NodeInstance": "BayerRaw2YuvInstance0",
            "InputFormat": "RAW16",
            "OutputFormat": "YUV420_NV12"
        },
        {
            "NodeName": "com.xiaomi.plugin.offlinepostproc",
            "NodeInstance": "BayerRaw2YuvInstance1",
            "InputFormat": "RAW16",
            "OutputFormat": "YUV420_NV12",
			"NodeProperty":[
			  {
				  "NodePropertyName":"NodeMask",
				  "NodePropertyValue":12
			  }
			  ]
        },
        {
            "NodeName": "com.xiaomi.plugin.capdepth",
            "NodeInstance": "CapdepthInstance0",
            "InputFormat": "YUV420_NV12",
            "OutputFormat": "YUV420_NV12",
            "NodeProperty":[
            {
                "NodePropertyName":"NodeMask",
                "NodePropertyValue":4
            }
            ]
        },
        {
            "NodeName": "com.xiaomi.plugin.caphdr",
            "NodeInstance": "CaphdrInstance0",
            "InputFormat": "YUV420_NV12",
            "OutputFormat": "YUV420_NV12",
            "NodeProperty":[
            {
                "NodePropertyName":"NodeMask",
                "NodePropertyValue":4
            }
            ]
        },
        {
            "NodeName": "com.xiaomi.plugin.memcpy",
            "NodeInstance": "MemcpyInstance0",
            "InputFormat": "YUV420_NV12",
            "OutputFormat": "YUV420_NV12",
            "NodeProperty":[
            {
                "NodePropertyName":"NodeMask",
                "NodePropertyValue":4
            }
            ]
        },
        {
            "NodeName": "com.xiaomi.plugin.arcsoftsll",
            "NodeInstance": "ArcsoftSLLInstance0",
            "InputFormat": "RAW16",
            "OutputFormat": "RAW16",
            "NodeProperty":[
            {
                "NodePropertyName":"NodeMask",
                "NodePropertyValue":16
            }
            ]
        },
        {
            "NodeName": "com.xiaomi.plugin.offlinepostproc",
            "NodeInstance": "IdealRaw2YuvInstance0",
            "InputFormat": "RAW16",
            "OutputFormat": "YUV420_NV12",
            "NodeProperty":[
            {
                "NodePropertyName":"NodeMask",
                "NodePropertyValue":4
            }
            ]
        },
        {
            "NodeName": "com.xiaomi.plugin.anchor",
            "NodeInstance": "anchorInstance0",
            "NodeProperty":[
            {
                "NodePropertyName":"NodeMask",
                "NodePropertyValue":1
            }
            ]
        },
        {
            "NodeName": "com.xiaomi.plugin.virtual",
            "NodeInstance": "virtualInstance0",
            "NodeProperty":[
            {
                "NodePropertyName":"NodeMask",
                "NodePropertyValue":512
            }
            ]
        },
        {
            "NodeName": "com.xiaomi.plugin.offlinepostproc",
            "NodeInstance": "JpegInstance0",
            "InputFormat": "YUV420_NV12",
            "OutputFormat": "BLOB"
        }
      ]
    },
    "PortLinkages": {
        "Link": [
            {
                "SrcPort": {
                "PortId": 0,
                "NodeInstance": "SourceBuffer0"
                },
                "DstPort": {
                "PortId": 0,
                "NodeInstance": "ArcsoftSLLInstance0"
                }
            },
            {
                "SrcPort": {
                "PortId": 0,
                "NodeInstance": "ArcsoftSLLInstance0"
                },
                "DstPort": {
                "PortId": 0,
                "NodeInstance": "IdealRaw2YuvInstance0"
                }
            },
            {
                "SrcPort": {
                    "PortId": 0,
                    "NodeInstance": "IdealRaw2YuvInstance0"
                },
                "DstPort": {
                    "PortId": 0,
                    "NodeInstance": "virtualInstance0"
                }
            },
            {
                "SrcPort": {
                    "PortId": 1,
                    "NodeInstance": "virtualInstance0"
                },
                "DstPort": {
                    "PortId": 0,
                    "NodeInstance": "CapdepthInstance0"
                }
            },
            {
                "SrcPort": {
                    "PortId": 0,
                    "NodeInstance": "virtualInstance0"
                },
                "DstPort": {
                    "PortId": 0,
                    "NodeInstance": "CaphdrInstance0"
                }
            },
            {
                "SrcPort": {
                    "PortId": 0,
                    "NodeInstance": "CaphdrInstance0"
                },
                "DstPort": {
                    "PortId": 0,
                    "NodeInstance": "CapbokehInstance0"
                }
            },
            {
                "SrcPort": {
                    "PortId": 1,
                    "NodeInstance": "SourceBuffer1"
                },
                "DstPort": {
                    "PortId": 0,
                    "NodeInstance": "anchorInstance0"
                }
            },
            {
                "SrcPort": {
                    "PortId": 0,
                    "NodeInstance": "anchorInstance0"
                },
                "DstPort": {
                    "PortId": 0,
                    "NodeInstance": "BayerRaw2YuvInstance0"
                }
            },
            {
                "SrcPort": {
                    "PortId": 0,
                    "NodeInstance": "BayerRaw2YuvInstance0"
                },
                "DstPort": {
                    "PortId": 1,
                    "NodeInstance": "CapdepthInstance0"
                }
            },
            {
                "SrcPort": {
                    "PortId": 0,
                    "NodeInstance": "CapdepthInstance0"
                },
                "DstPort": {
                    "PortId": 1,
                    "NodeInstance": "CapbokehInstance0"
                }
            },
            {
                "SrcPort": {
                    "PortId": 0,
                    "NodeInstance": "CapbokehInstance0"
                },
                "DstPort": {
                    "PortId": 0,
                    "NodeInstance": "JpegInstance0"
                }
            },
            {
                "SrcPort": {
                    "PortId": 0,
                    "NodeInstance": "JpegInstance0"
                },
                "DstPort": {
                    "PortId": 0,
                    "NodeInstance": "SinkBuffer0"
                }
            }
        ]
    }
  }
  